opentone
