Metadata-Version: 1.0
Name: opentone
Version: 0.1.2
Summary: DTMF utils
Home-page: UNKNOWN
Author: jarbasAI
Author-email: jarbasai@mailfence.com
License: MIT
Platform: UNKNOWN
